imagecompression7/__init__.py
imagecompression7/algorithm.py
imagecompression7/image_untils.py
imagecompression7/image_utils.py
imagecompression7-0.1.13.dist-info/LICENSE.txt
imagecompression7-0.1.13.dist-info/METADATA
imagecompression7-0.1.13.dist-info/WHEEL
imagecompression7-0.1.13.dist-info/top_level.txt
imagecompression7-0.1.13.dist-info/RECORD
